mpf_monitor-0.57.2.dist-info/licenses/LICENSE
mpfmonitor/__init__.py
mpfmonitor/_version.py
mpfmonitor/commands/monitor.py
mpfmonitor/core/bcp_client.py
mpfmonitor/core/devices.py
mpfmonitor/core/events.py
mpfmonitor/core/inspector.py
mpfmonitor/core/modes.py
mpfmonitor/core/mpfmon.py
mpfmonitor/core/playfield.py
mpfmonitor/core/variables.py
mpfmonitor/core/ui/inspector.ui
mpfmonitor/core/ui/searchable_table.ui
mpfmonitor/core/ui/searchable_tree.ui
mpfmonitor/tests/test_devices.py
mpfmonitor/tests/test_events.py
mpfmonitor/tests/test_inspector.py
mpfmonitor/tests/test_modes.py
mpfmonitor/tests/test_mpfmon.py
mpfmonitor/tests/test_playfield.py
mpf_monitor-0.57.2.dist-info/METADATA
mpf_monitor-0.57.2.dist-info/WHEEL
mpf_monitor-0.57.2.dist-info/entry_points.txt
mpf_monitor-0.57.2.dist-info/top_level.txt
mpf_monitor-0.57.2.dist-info/RECORD
