Metadata-Version: 2.4
Name: mpf-monitor
Version: 0.57.2
Summary: MPF Monitor
Author-email: The Mission Pinball Framework Team <brian@fastpinball.com>
License: MIT
Project-URL: homepage, https://missionpinball.org
Keywords: pinball,mpf
Classifier: Development Status :: 4 - Beta
Classifier: Intended Audience :: Developers
Classifier: License :: OSI Approved :: MIT License
Classifier: Programming Language :: Python :: 3.8
Classifier: Programming Language :: Python :: 3.9
Classifier: Programming Language :: Python :: 3.10
Classifier: Programming Language :: Python :: 3.11
Classifier: Programming Language :: Python :: 3.12
Classifier: Programming Language :: Python :: 3.13
Classifier: Natural Language :: English
Classifier: Operating System :: MacOS :: MacOS X
Classifier: Operating System :: Microsoft :: Windows
Classifier: Operating System :: POSIX :: Linux
Classifier: Topic :: Artistic Software
Classifier: Topic :: Games/Entertainment :: Arcade
Requires-Python: >=3.8
License-File: LICENSE
Requires-Dist: PyQt6>=6.4.2
Requires-Dist: Pillow>=10.4.0
Dynamic: license-file
